edges/__init__.py
edges/analysis.py
edges/costs.py
edges/edgelcia.py
edges/filesystem_constants.py
edges/flow_matching.py
edges/georesolver.py
edges/logging_config.py
edges/matrix_builders.py
edges/supply_chain.py
edges/uncertainty.py
edges/utils.py
edges/data/AWARE 2.0_Country_all_yearly.json
edges/data/AWARE 2.0_Country_irri_yearly.json
edges/data/AWARE 2.0_Country_non_irri_yearly.json
edges/data/AWARE 2.0_Country_unspecified_yearly.json
edges/data/GLAM3_biodiversity_occupation_average_amphibians.json
edges/data/GLAM3_biodiversity_occupation_average_birds.json
edges/data/GLAM3_biodiversity_occupation_average_eukaryota.json
edges/data/GLAM3_biodiversity_occupation_average_mammals.json
edges/data/GLAM3_biodiversity_occupation_average_plants.json
edges/data/GLAM3_biodiversity_occupation_average_reptiles.json
edges/data/GLAM3_biodiversity_transformation_average_amphibians.json
edges/data/GLAM3_biodiversity_transformation_average_birds.json
edges/data/GLAM3_biodiversity_transformation_average_eukaryota.json
edges/data/GLAM3_biodiversity_transformation_average_mammals.json
edges/data/GLAM3_biodiversity_transformation_average_plants.json
edges/data/GLAM3_biodiversity_transformation_average_reptiles.json
edges/data/GeoPolRisk_paired_2024.json
edges/data/IBIF_biodiversity_CO2_overall.json
edges/data/IBIF_biodiversity_CO2_plants.json
edges/data/IBIF_biodiversity_CO2_vertebrates.json
edges/data/IBIF_biodiversity_LU_overall.json
edges/data/IBIF_biodiversity_LU_plants.json
edges/data/IBIF_biodiversity_LU_vertebrates.json
edges/data/IBIF_biodiversity_NH3_overall.json
edges/data/IBIF_biodiversity_NH3_plants.json
edges/data/IBIF_biodiversity_NOx_overall.json
edges/data/IBIF_biodiversity_NOx_plants.json
edges/data/IBIF_biodiversity_all pressures_overall.json
edges/data/IBIF_biodiversity_all pressures_plants.json
edges/data/IBIF_biodiversity_all pressures_vertebrates.json
edges/data/ImpactWorld+ 2.1_Freshwater acidification_damage.json
edges-1.0.8.dist-info/METADATA
edges-1.0.8.dist-info/WHEEL
edges-1.0.8.dist-info/top_level.txt
edges-1.0.8.dist-info/RECORD
