Metadata-Version: 2.4
Name: edges
Version: 1.0.8
Summary: Country-specific characterization factors for the Brightway LCA framework
Author-email: Romain Sacchi <romain.sacchi@psi.ch>, Alvaro Hahn Menacho <alvaro.hahn-menacho@psi.ch>
Maintainer-email: Romain Sacchi <romain.sacchi@psi.ch>
Project-URL: source, https://github.com/Laboratory-for-Energy-Systems-Analysis/clear-scope
Project-URL: homepage, https://github.com/Laboratory-for-Energy-Systems-Analysis/clear-scope
Project-URL: tracker, https://github.com/Laboratory-for-Energy-Systems-Analysis/clear-scope/issues
Classifier: Intended Audience :: Science/Research
Classifier: License :: OSI Approved :: BSD License
Classifier: Natural Language :: English
Classifier: Programming Language :: Python :: 3
Classifier: Operating System :: OS Independent
Classifier: Topic :: Scientific/Engineering
Requires-Python: <3.13,>=3.10
Requires-Dist: numpy
Requires-Dist: pandas
Requires-Dist: scipy
Requires-Dist: pyyaml
Requires-Dist: country_converter>=1.3.1
Requires-Dist: constructive_geometries>=1.0.0
Requires-Dist: prettytable
Requires-Dist: sparse>=0.13.0
Requires-Dist: plotly
Requires-Dist: ecoinvent_interface
Requires-Dist: highspy
Requires-Dist: packaging
Provides-Extra: testing
Requires-Dist: setuptools; extra == "testing"
Requires-Dist: pytest; extra == "testing"
Provides-Extra: docs
Requires-Dist: sphinx-rtd-theme; extra == "docs"
